isopeptor/__init__.py
isopeptor/asa.py
isopeptor/bond.py
isopeptor/bond_length.py
isopeptor/cli.py
isopeptor/constants.py
isopeptor/dihedrals.py
isopeptor/isopeptide.py
isopeptor/jess_wrapper.py
isopeptor/logistic_regression.py
isopeptor/resources/data/template_structures/1amx_A_176_209_293.pdb
isopeptor/resources/data/template_structures/2f68_X_176_209_293.pdb
isopeptor/resources/data/template_structures/2okm_A_42_74_155.pdb
isopeptor/resources/data/template_structures/2woy_A_1259_1307_1393.pdb
isopeptor/resources/data/template_structures/2wqs_A_1259_1307_1393.pdb
isopeptor/resources/data/template_structures/2ww8_A_191_600_695.pdb
isopeptor/resources/data/template_structures/2ww8_A_742_803_854.pdb
isopeptor/resources/data/template_structures/2wza_A_1082_1132_1232.pdb
isopeptor/resources/data/template_structures/2wza_A_1259_1307_1393.pdb
isopeptor/resources/data/template_structures/2x5p_A_31_77_117.pdb
isopeptor/resources/data/template_structures/2x9w_A_193_241_318.pdb
isopeptor/resources/data/template_structures/2x9w_A_349_405_428.pdb
isopeptor/resources/data/template_structures/2x9w_A_453_577_623.pdb
isopeptor/resources/data/template_structures/2x9x_A_193_241_318.pdb
isopeptor/resources/data/template_structures/2x9x_A_349_405_428.pdb
isopeptor/resources/data/template_structures/2x9x_A_453_577_623.pdb
isopeptor/resources/data/template_structures/2x9y_A_193_241_318.pdb
isopeptor/resources/data/template_structures/2x9y_A_349_405_428.pdb
isopeptor/resources/data/template_structures/2x9y_A_453_577_623.pdb
isopeptor/resources/data/template_structures/2x9z_A_193_241_318.pdb
isopeptor/resources/data/template_structures/2x9z_A_349_405_428.pdb
isopeptor/resources/data/template_structures/2xi9_A_297_347_595.pdb
isopeptor/resources/data/template_structures/2xtl_A_199_247_325.pdb
isopeptor/resources/data/template_structures/2xtl_A_355_416_437.pdb
isopeptor/resources/data/template_structures/2xtl_A_463_589_636.pdb
isopeptor-0.0.80.dist-info/LICENSE
isopeptor-0.0.80.dist-info/METADATA
isopeptor-0.0.80.dist-info/WHEEL
isopeptor-0.0.80.dist-info/entry_points.txt
isopeptor-0.0.80.dist-info/RECORD
