Metadata-Version: 2.1
Name: isopeptor
Version: 0.0.80
Summary: Package for isopeptide bond prediction and analysis based on pyjess
Home-page: https://github.com/FranceCosta/isopeptor
License: MIT
Author: Francesco Costa
Author-email: fcosta@ebi.ac.uk
Requires-Python: >=3.10
Classifier: License :: OSI Approved :: MIT License
Classifier: Programming Language :: Python :: 3
Classifier: Programming Language :: Python :: 3.10
Classifier: Programming Language :: Python :: 3.11
Classifier: Programming Language :: Python :: 3.12
Classifier: Programming Language :: Python :: 3.13
Requires-Dist: biotite (==1.*)
Requires-Dist: joblib (==1.4.*)
Requires-Dist: numpy (==2.*)
Requires-Dist: pyjess (>=0.3.0,<0.5.0)
Requires-Dist: scikit-learn (>=1.5)
Project-URL: Documentation, https://github.com/FranceCosta/isopeptor/README.md
Project-URL: Repository, https://github.com/FranceCosta/isopeptor
